fractalistic/__init__.py
fractalistic/__main__.py
fractalistic/app.py
fractalistic/app.tcss
fractalistic/click_modes.py
fractalistic/colors.py
fractalistic/command.py
fractalistic/fractal_canv.py
fractalistic/line_divergence_result.py
fractalistic/settings.py
fractalistic/utils.py
fractalistic/vec.py
fractalistic/fractals/__init__.py
fractalistic/fractals/burning_ship.py
fractalistic/fractals/fractal_base.py
fractalistic/fractals/inv_mandel.py
fractalistic/fractals/julia.py
fractalistic/fractals/mandelbrot.py
fractalistic-2.3.0.dist-info/entry_points.txt
fractalistic-2.3.0.dist-info/LICENSE
fractalistic-2.3.0.dist-info/WHEEL
fractalistic-2.3.0.dist-info/METADATA
fractalistic-2.3.0.dist-info/RECORD
