Metadata-Version: 2.1
Name: fractalistic
Version: 2.3.0
Summary: Terminal based fractal explorer, that includes Mandelbrot, Burning Ship, and Julia.
Author-email: Leopold Koprivnik <skwal@etik.com>
Requires-Python: >=3.10
Classifier: License :: OSI Approved :: MIT License
Requires-Dist: textual==0.38.1
Requires-Dist: click_extra==4.7.1
Requires-Dist: gmpy2==2.2.0
Requires-Dist: pillow==10.3.0
Requires-Dist: asyncio==3.4.3
Requires-Dist: textual_canvas==0.2.0
Requires-Dist: rich>=13.7.1
Project-URL: Changelog, https://github.com/SkwalExe/fractalistic/blob/main/CHANGELOG.md
Project-URL: Repository, https://github.com/SkwalExe/fractalistic
